LICENSE
MANIFEST.in
README.md
setup.py
hautomation_gpio/__init__.py
hautomation_gpio/cmds.py
hautomation_gpio/deploy.py
hautomation_gpio/settings.py
hautomation_gpio/tests.py
hautomation_gpio/utils.py
hautomation_gpio.egg-info/PKG-INFO
hautomation_gpio.egg-info/SOURCES.txt
hautomation_gpio.egg-info/dependency_links.txt
hautomation_gpio.egg-info/entry_points.txt
hautomation_gpio.egg-info/requires.txt
hautomation_gpio.egg-info/top_level.txt