Metadata-Version: 1.1
Name: hautomation-gpio
Version: 0.7
Summary: Home Automation Python Project Plugin for Raspberry PI GPIO
Home-page: http://blog.digitalhigh.es
Author: Javier Pardo Blasco(jpardobl)
Author-email: jpardo@digitalhigh.es
License: BSD License
Platform: UNKNOWN
Classifier: Intended Audience :: Developers
Classifier: License :: OSI Approved :: BSD License
Classifier: Operating System :: OS Independent
Classifier: Programming Language :: Python
Classifier: Programming Language :: Python :: 2.6
Classifier: Programming Language :: Python :: 2.7
Classifier: Topic :: Home Automation
